LICENSE
README.md
burpless/Burpless.py
burpless/Cli.py
burpless/Grammar.py
burpless/Indenter.py
burpless/Parser.py
burpless/Transformer.py
burpless/Tree.py
burpless/Version.py
burpless/__init__.py
grammar/grammar.ebnf
burpless-0.1.2.dist-info/entry_points.txt
burpless-0.1.2.dist-info/LICENSE
burpless-0.1.2.dist-info/WHEEL
burpless-0.1.2.dist-info/METADATA
burpless-0.1.2.dist-info/RECORD
